{
  "games": 100,
  "black_wins": 45,
  "white_wins": 55,
  "draws": 0,
  "avg_steps": 26.77,
  "black_timeouts": 0,
  "white_timeouts": 0,
  "black_fouls": 0,
  "white_fouls": 0,
  "black_invalid_moves": 0,
  "white_invalid_moves": 0,
  "black_tag": "black",
  "white_tag": "white",
  "swap_colors": true,
  "agent_games": {
    "black": 100,
    "white": 100
  },
  "agent_wins": {
    "black": 57,
    "white": 43
  },
  "agent_draws": {},
  "agent_points": {
    "black": 57.0,
    "white": 43.0
  }
}